ScraGet/Exceptions.py
ScraGet/ScraGet.py
ScraGet/__init__.py
ScraGet/cloud.py
ScraGet/encoder.py
ScraGet/forum.py
ScraGet/frontpage.py
ScraGet/project.py
ScraGet/studios.py
ScraGet/user.py
ScraGet-0.2.4.dist-info/LICENSE
ScraGet-0.2.4.dist-info/METADATA
ScraGet-0.2.4.dist-info/WHEEL
ScraGet-0.2.4.dist-info/top_level.txt
ScraGet-0.2.4.dist-info/RECORD
