Metadata-Version: 2.1
Name: ScraGet
Version: 0.2.4
Summary: A package that makes interacting with Scratch API easier
Home-page: https://github.com/Quantum-Codes/ScraGet
License: MIT
Project-URL: Get help, https://github.com/Quantum-Codes/ScraGet/discussions
Project-URL: Source, https://github.com/Quantum-Codes/ScraGet/tree/master/ScraGet
Project-URL: Bug Tracker, https://github.com/Quantum-Codes/ScraGet/issues
Project-URL: Documentation, https://github.com/Quantum-Codes/ScraGet/wiki
Keywords: Scratch,ScraGet,API,ScratchAPI,Scratch-API,Scratch3,ScratchCloud,Cloud
Platform: UNKNOWN
Classifier: Programming Language :: Python :: 3
Classifier: License :: OSI Approved :: MIT License
Classifier: Operating System :: OS Independent
Requires-Python: >=3.6
Requires-Dist: requests
